Metadata-Version: 2.1
Name: demo-package-checker
Version: 0.0.2
Summary: demo package
Home-page: https://github.com/slicemenice/demo_package_checker
Author: Demo
Author-email: demo@gmail.com
License: MIT
Platform: UNKNOWN
Classifier: Programming Language :: Python :: 3
Classifier: License :: OSI Approved :: MIT License
Classifier: Operating System :: OS Independent
Requires: cryptography
Requires: requests
Requires-Python: >=3.6
License-File: LICENSE
